siphon/__init__.py
siphon/agent/__init__.py
siphon/agent/runner.py
siphon/agent/agent_components/__init__.py
siphon/agent/agent_components/llm.py
siphon/agent/agent_components/stt.py
siphon/agent/agent_components/tts.py
siphon/agent/core/__init__.py
siphon/agent/core/entrypoint.py
siphon/agent/core/utils.py
siphon/agent/core/voice_agent.py
siphon/agent/internal_prompts/__init__.py
siphon/agent/internal_prompts/call_agent.py
siphon/agent/internal_prompts/datetime_awareness.py
siphon/agent/internal_prompts/proactive_behavior.py
siphon/config/__init__.py
siphon/config/call_metadata.py
siphon/config/call_recording.py
siphon/config/call_transcription.py
siphon/config/data_storage.py
siphon/config/hangup_call.py
siphon/config/logging_config.py
siphon/config/timezone_utils.py
siphon/integrations/__init__.py
siphon/integrations/date_time/datetime_tool.py
siphon/integrations/google_calendar/calendar.py
siphon/integrations/google_calendar/services.py
siphon/plugins/__init__.py
siphon/plugins/anthropic.py
siphon/plugins/assemblyai.py
siphon/plugins/cartesia.py
siphon/plugins/cerebras.py
siphon/plugins/deepgram.py
siphon/plugins/deepseek.py
siphon/plugins/elevenlabs.py
siphon/plugins/gemini.py
siphon/plugins/google.py
siphon/plugins/groq.py
siphon/plugins/mistralai.py
siphon/plugins/ollama.py
siphon/plugins/openai.py
siphon/plugins/openrouter.py
siphon/plugins/perplexity.py
siphon/plugins/rime.py
siphon/plugins/sarvam.py
siphon/plugins/together.py
siphon/plugins/xai.py
siphon/telephony/__init__.py
siphon/telephony/inbound/__init__.py
siphon/telephony/inbound/dispatch.py
siphon/telephony/inbound/trunk.py
siphon/telephony/outbound/__init__.py
siphon/telephony/outbound/make_call.py
siphon/telephony/outbound/trunk.py
siphon_ai-0.1.2.dist-info/METADATA
siphon_ai-0.1.2.dist-info/WHEEL
siphon_ai-0.1.2.dist-info/licenses/LICENSE
siphon_ai-0.1.2.dist-info/RECORD
