Metadata-Version: 2.4
Name: siphon-ai
Version: 0.1.2
Summary: Build calling agents in minutes, not months. The missing infrastructure layer for AI calling. Siphon handles state, interruptions, and scaling so you can ship reliable agents in minutes, not months.
Project-URL: Homepage, https://siphon.blackdwarf.in/
Project-URL: Source, https://github.com/blackdwarftech/siphon
Author-email: BLACKDWARF <hi@blackdwarf.in>
License: Apache-2.0
License-File: LICENSE
Keywords: ai-call-processing,ai-calling,ai-calling-crm-integration,ai-phone-systems,ai-telephony,ai-voice-systems,automated-calling,call-analytics,call-center,call-routing,calling-agent,contact-center,contact-center-solutions,conversational-ai,ivr,ivr-systems,livekit,livekit-agents,pstn,realtime,realtime-ai,sip,speech-to-text,telephony,telephony-ai-solutions,telephony-api,telephony-automation,telephony-crm-integration,telephony-devices,telephony-integrations,telephony-platform,telephony-sdk,tele
Classifier: Intended Audience :: Developers
Classifier: License :: OSI Approved :: Apache Software License
Classifier: Natural Language :: English
Classifier: Operating System :: OS Independent
Classifier: Programming Language :: Python :: 3
Classifier: Programming Language :: Python :: 3 :: Only
Classifier: Topic :: Software Development :: Libraries :: Python Modules
Classifier: Typing :: Typed
Requires-Python: >=3.10
Requires-Dist: boto3
Requires-Dist: google-api-python-client
Requires-Dist: google-auth-httplib2
Requires-Dist: google-auth-oauthlib
Requires-Dist: livekit
Requires-Dist: livekit-agents
Requires-Dist: livekit-agents[anthropic]
Requires-Dist: livekit-agents[assemblyai]
Requires-Dist: livekit-agents[cartesia]
Requires-Dist: livekit-agents[deepgram]
Requires-Dist: livekit-agents[elevenlabs]
Requires-Dist: livekit-agents[google]
Requires-Dist: livekit-agents[groq]
Requires-Dist: livekit-agents[mistralai]
Requires-Dist: livekit-agents[openai]
Requires-Dist: livekit-agents[rime]
Requires-Dist: livekit-agents[sarvam]
Requires-Dist: livekit-agents[silero]
Requires-Dist: livekit-agents[turn-detector]
Requires-Dist: livekit-api
Requires-Dist: livekit-plugins-noise-cancellation
Requires-Dist: psycopg2
Requires-Dist: pymongo
Requires-Dist: python-dotenv
Requires-Dist: redis
Requires-Dist: sqlalchemy
